bioio_sldy/__init__.py
bioio_sldy/py.typed
bioio_sldy/reader.py
bioio_sldy/reader_metadata.py
bioio_sldy/sldy_image.py
bioio_sldy-1.4.1.dist-info/licenses/LICENSE
scripts/benchmark.py
bioio_sldy-1.4.1.dist-info/METADATA
bioio_sldy-1.4.1.dist-info/WHEEL
bioio_sldy-1.4.1.dist-info/entry_points.txt
bioio_sldy-1.4.1.dist-info/top_level.txt
bioio_sldy-1.4.1.dist-info/RECORD
